pws256/__init__.py
pws256/rsa.py
pws256/users.py
pws256/_setup/rsasrcimport.py
pws256/_setup/setup.py
pws256/_setup/srcimport.py
pws256/_setup/usersrcimport.py
pws256/src/__init__.py
pws256/src/base.py
pws256/src/rsa.py
pws256/src/users.py
pws256-1.1.14.dist-info/METADATA
pws256-1.1.14.dist-info/WHEEL
pws256-1.1.14.dist-info/top_level.txt
pws256-1.1.14.dist-info/RECORD
