Metadata-Version: 2.1
Name: pws256
Version: 1.1.14
Summary: pws256: A module that is used for users and passwords, and also has validation methods to check passwords with strings
Author: Hector Robertson
Requires-Dist: numpy
